tpg366_ioc/__init__.py
tpg366_ioc/_version.py
tpg366_ioc/main.py
tpg366_ioc-0.1.1.dist-info/licenses/COPYING.md
tpg366_ioc-0.1.1.dist-info/METADATA
tpg366_ioc-0.1.1.dist-info/WHEEL
tpg366_ioc-0.1.1.dist-info/entry_points.txt
tpg366_ioc-0.1.1.dist-info/top_level.txt
tpg366_ioc-0.1.1.dist-info/RECORD
