Metadata-Version: 2.4
Name: tpg366-ioc
Version: 0.1.1
Summary: Command-line client tools for EPICS-CA data processing
Author-email: Florin Boariu <florin.pt@rootshell.ro>
License-Expression: GPL-3.0-or-later
Project-URL: Source Code, https://gitlab.com/kmc3-xpp/caspy
Project-URL: Bug Tracker, https://gitlab.com/kmc3-xpp/caspy/-/issues
Classifier: Programming Language :: Python :: 3
Classifier: Operating System :: POSIX :: Linux
Classifier: Development Status :: 2 - Pre-Alpha
Classifier: Environment :: Console
Classifier: Intended Audience :: Science/Research
Classifier: Topic :: Scientific/Engineering
Requires-Python: >=3.8
License-File: COPYING.md
Requires-Dist: caproto
Requires-Dist: numpy
Requires-Dist: pyvisa
Provides-Extra: all
Requires-Dist: tpg366_ioc[test]; extra == "all"
Provides-Extra: test
Requires-Dist: pytest; extra == "test"
Requires-Dist: pytest-cov; extra == "test"
Requires-Dist: pytest-asyncio; extra == "test"
Dynamic: license-file
